transcov/__init__.py
transcov/bam.py
transcov/cli.py
transcov/generator.py
transcov/manipulations.py
transcov/plotter.py
transcov/preprocessor.py
transcov/transcript_annotation.py
transcov/tss.py
transcov/utils.py
transcov-1.1.3.dist-info/DESCRIPTION.rst
transcov-1.1.3.dist-info/METADATA
transcov-1.1.3.dist-info/RECORD
transcov-1.1.3.dist-info/WHEEL
transcov-1.1.3.dist-info/entry_points.txt
transcov-1.1.3.dist-info/metadata.json
transcov-1.1.3.dist-info/top_level.txt
