Metadata-Version: 2.0
Name: transcov
Version: 1.1.3
Summary: A software for mapping coverage around transcription start sites
Home-page: https://github.com/hogfeldt/transcov
Author: Per Høgfeldt
License: UNKNOWN
Platform: UNKNOWN
Classifier: Programming Language :: Python :: 3
Classifier: License :: OSI Approved :: GNU General Public License v3 (GPLv3)
Classifier: Operating System :: OS Independent
Requires-Python: >=3.6
Requires-Dist: attrs
Requires-Dist: click (>=7.0)
Requires-Dist: matplotlib
Requires-Dist: numpy
Requires-Dist: pandas
Requires-Dist: pysam
Requires-Dist: scipy
Requires-Dist: seaborn
